{
    "md5": "c8e794a6b9abf8d275ef1d4a15a8fa67",
    "releaseDate": "28/06/2023",
    "title": {
        "it": "Newsletter del 28 giugno 2023 - Fidelity card: il Garante privacy sanziona il Gruppo Benetton - Garante: stop al web scraping per formare elenchi telefonici - Garante privacy: illecite le email pubblicitarie senza consenso - Garante privacy, no al diritto all’oblio per reati gravi"
    },
    "url": "https://www.garanteprivacy.it/web/guest/home/docweb/-/docweb-display/docweb/9903191"
}