{
    "md5": "3c96dd692dbf10dddae1f9984c68b419",
    "releaseDate": "08/02/2019",
    "title": {
        "el": "Προειδοποίηση σε δημόσιο νοσοκομείο για μη ενημέρωση ασθενούς του σχετικά με διαβίβαση δεδομένων ιατρικού του φακέλου σε τρίτον για δικαστική χρήση (διαδικασία εργατικών διαφορών)"
    },
    "url": "https://www.dpa.gr/el/enimerwtiko/prakseisArxis/proeidopoiisi-se-dimosio-nosokomeio-gia-mi-enimerosi-asthenoys-toy",
    "decision": "warning",
    "fine": "0",
    "controller": "General Hospital of Thessaloniki \"Papageorgiou\"",
    "articles": "13"
}