{
    "md5": "a9784238fc65bb6388d685decf037451",
    "releaseDate": "15/12/2022",
    "title": {
        "da": "Tilsyn med Forsvarsministeriets Personalestyrelses tilsyn med to databehandlere"
    },
    "url": "https://www.datatilsynet.dk/afgoerelser/afgoerelser/2022/dec/tilsyn-med-forsvarsministeriets-personalestyrelses-tilsyn-med-to-databehandlere",
    "decision": "in accordance with the rules",
    "fine": "0",
    "controller": "Ministry of Defence's Personnel Board",
    "articles": "5"
}