{
    "md5": "2a600a3132154fe32f1475d6311a4dce",
    "releaseDate": "25/09/2019",
    "title": {
        "el": "ΑΝΟΝΥΜΟΠΟΙΗΜΕΝΗ ΑΠΟΦΑΣΗ ΕΝΑΝΤΙΟΝ ΔΗΜΟΤΙΚΟΥ ΣΥΜΒΟΥΛΟΥ_.pdf"
    },
    "url": "https://www.dataprotection.gov.cy/dataprotection/dataprotection.nsf/0FE8ABFD413427C8C2258488002E4FF1/$file/%CE%91%CE%9D%CE%9F%CE%9D%CE%A5%CE%9C%CE%9F%CE%A0%CE%9F%CE%99%CE%97%CE%9C%CE%95%CE%9D%CE%97%20%CE%91%CE%A0%CE%9F%CE%A6%CE%91%CE%A3%CE%97%20%CE%95%CE%9D%CE%91%CE%9D%CE%A4%CE%99%CE%9F%CE%9D%20%CE%94%CE%97%CE%9C%CE%9F%CE%A4%CE%99%CE%9A%CE%9F%CE%A5%20%CE%A3%CE%A5%CE%9C%CE%92%CE%9F%CE%A5%CE%9B%CE%9F%CE%A5_.pdf",
    "decision": "administrative fine",
    "fine": "1,000",
    "controller": "unnamed municipality",
    "articles": "4, 5, 6, 32"
}