{
    "md5": "8b87dfd7229750aa40faf91b773b71d5",
    "releaseDate": "24/06/2021",
    "title": {
        "it": "Ordinanza ingiunzione nei confronti di Istituto Professionale per i servizi commerciali e turistici “G. Ravizza” di Novara - 24 giugno 2021 [9688099]"
    },
    "url": "https://www.garanteprivacy.it/web/guest/home/docweb/-/docweb-display/docweb/9688099",
    "fine": "2000",
    "controller": "the Professional Institute for commercial and tourist services “G. Ravizza ”in Novara",
    "articles": "5, 6, 9"
}
