{
    "md5": "e2c0b6a7a6cf9e8a9d7fcd16873879e1",
    "releaseDate": "17/04/2019",
    "title": {
        "hu": "A hozzáférési jog gyakorlásának biztosítása; a GDPR 6. cikk (1) bekezdés b) pontja szerinti jogalap alkalmazása"
    },
    "url": "https://www.naih.hu//hatarozatok-vegzesek?download=160:a-hozzaferesi-jog-gyakorlasanak-biztositasa-a-gdpr-6-cikk-1-bekezdes-b-pontja-szerinti-jogalap-alkalmazasa&start=100",
    "decision": "partial illegal data processing",
    "fine": "2,701",
    "controller": "the Applicant",
    "articles": "2, 5, 6, 12, 15, 22, 58"
}
