{
  "AT": {
    "code": "EUR",
    "symbol": "€",
    "plural": ["euro", "euros"]
  },
  "BE": {
    "code": "EUR",
    "symbol": "€",
    "plural": ["euro", "euros"]
  },
  "BG": {
    "code": "BGN",
    "symbol": null,
    "plural": ["levove", "leva"]
  },
  "CY": {
    "code": "EUR",
    "symbol": "€",
    "plural": ["euro", "euros"]
  },
  "CZ": {
    "code": "CZK",
    "symbol": "Kč",
    "plural": []
  },
  "DE": {
    "code": "EUR",
    "symbol": "€",
    "plural": ["euro", "euros"]
  },
  "DK": {
    "code": "DKK",
    "symbol": "kr.",
    "plural": ["kroner"]
  },
  "EE": {
    "code": "EUR",
    "symbol": "€",
    "plural": ["euro", "euros"]
  },
  "ES": {
    "code": "EUR",
    "symbol": "€",
    "plural": ["euro", "euros"]
  },
  "FI": {
    "code": "EUR",
    "symbol": "€",
    "plural": ["euro", "euros"]
  },
  "FR": {
    "code": "EUR",
    "symbol": "€",
    "plural": ["euro", "euros"]
  },
  "GB": {
    "code": "GBP",
    "symbol": "£",
    "plural": ["pounds"]
  },
  "GR": {
    "code": "EUR",
    "symbol": "€",
    "plural": ["euro", "euros"]
  },
  "HR": {
    "code": "HRK",
    "symbol": "kn",
    "plural": []
  },
  "HU": {
    "code": "HUF",
    "symbol": "Ft",
    "plural": ["forintok"]
  },
  "IE": {
    "code": "EUR",
    "symbol": "€",
    "plural": ["euro", "euros"]
  },
  "IT": {
    "code": "EUR",
    "symbol": "€",
    "plural": ["euro", "euros"]
  },
  "LT": {
    "code": "EUR",
    "symbol": "€",
    "plural": ["euro", "euros"]
  },
  "LU": {
    "code": "EUR",
    "symbol": "€",
    "plural": ["euro", "euros"]
  },
  "LV": {
    "code": "EUR",
    "symbol": "€",
    "plural": ["euro", "euros"]
  },
  "MT": {
    "code": "EUR",
    "symbol": "€",
    "plural": ["euro", "euros"]
  },
  "NL": {
    "code": "EUR",
    "symbol": "€",
    "plural": ["euro", "euros"]
  },
  "LV": {
    "code": "EUR",
    "symbol": "€",
    "plural": ["euro", "euros"]
  },
  "PO": {
    "code": "PLN",
    "symbol": "zł",
    "plural": []
  },
  "PT": {
    "code": "EUR",
    "symbol": "€",
    "plural": ["euro", "euros"]
  },
  "RO": {
    "code": "RON",
    "symbol": "L",
    "plural": ["lei"]
  },
  "SE": {
    "code": "SEK",
    "symbol": "kr",
    "plural": ["kronor"]
  },
  "SI": {
    "code": "EUR",
    "symbol": "€",
    "plural": ["euro", "euros"]
  },
  "SK": {
    "code": "EUR",
    "symbol": "€",
    "plural": ["euro", "euros"]
  }
}
