{
    "md5": "892210c9133bb609afc85f27a7b4091b",
    "releaseDate": "30/04/2021",
    "title": {
        "fi": "Administrative fine imposed on company for data protection violations connected to parking control fees"
    },
    "url": "https://tietosuoja.fi/en/-/administrative-fine-imposed-on-company-for-data-protection-violations-connected-to-parking-control-fees",
    "decision": "administrative fine",
    "fine": "75,000",
    "controller": "ParkkiPate Oy",
    "articles": "5, 12, 14, 15, 17, 25",
    "RTBF component": "user interface, verification, policy resolution"
}