{
    "md5": "7dc33fb1ad6a755d6778549c794b948a",
    "releaseDate": "date not available",
    "title": {
        "cz": "Kontrola zabezpe\u010den\u00ed osobn\u00edch \u00fadaj\u016f v N\u00e1rodn\u00edm zdravotn\u00edm informa\u010dn\u00edm syst\u00e9mu (\u00dastav zdravotnick\u00fdch informac\u00ed a statistiky)"
    },
    "url": "https://www.uoou.cz/kontrola%2Dzabezpeceni%2Dosobnich%2Dudaju%2Dv%2Dnarodnim%2Dzdravotnim%2Dinformacnim%2Dsystemu%2Dustav%2Dzdravotnickych%2Dinformaci%2Da%2Dstatistiky/ds-5195/archiv=0&p1=1277"
}